pdecrypto/__init__.py
pdecrypto/core.py
pdecrypto/exceptions.py
pdecrypto/hashing.py
pdecrypto/utils.py
pdecrypto/tests/__init__.py
pdecrypto/tests/test.py
pdecrypto-0.1.1.dist-info/METADATA
pdecrypto-0.1.1.dist-info/WHEEL
pdecrypto-0.1.1.dist-info/top_level.txt
pdecrypto-0.1.1.dist-info/RECORD
