Metadata-Version: 2.4
Name: pdecrypto
Version: 0.1.1
Summary: Position-Dependent Encryption (PDE) library with authentication and padding
Home-page: https://github.com/QKing-Official/pdecrypto
Author: QKing
Author-email: qking@host4you.cloud
License: MIT
Classifier: Programming Language :: Python :: 3
Classifier: License :: OSI Approved :: MIT License
Classifier: Operating System :: OS Independent
Classifier: Topic :: Security :: Cryptography
Requires-Python: >=3.7
Requires-Dist: pytest>=7.0.0
Dynamic: author
Dynamic: author-email
Dynamic: classifier
Dynamic: description
Dynamic: description-content-type
Dynamic: home-page
Dynamic: license
Dynamic: requires-dist
Dynamic: requires-python
Dynamic: summary
